{
  "aor": 0.0033101418439716312,
  "aqi": 0.009475308439716312,
  "bids_meta": {
    "EchoTime": 0.03,
    "FlipAngle": 71,
    "RepetitionTime": 2,
    "SliceTiming": [
      1,
      0,
      1.055,
      0.055,
      1.11,
      0.11,
      1.165,
      0.165,
      1.22,
      0.2225,
      1.2775,
      0.2775,
      1.3325,
      0.3325,
      1.3875,
      0.3875,
      1.4425,
      0.4425,
      1.5,
      0.5,
      1.555,
      0.555,
      1.61,
      0.61,
      1.665,
      0.665,
      1.72,
      0.72,
      1.7775,
      0.7775,
      1.8325,
      0.8325,
      1.8875,
      0.8875,
      1.9425,
      0.9425
    ],
    "TaskName": "Study-Test",
    "dataset": "ds001745",
    "modality": "bold",
    "run_id": 6,
    "subject_id": "04",
    "task_id": "StudyTest"
  },
  "dummy_trs": 1,
  "dvars_nstd": 24.1604273115,
  "dvars_std": 1.2199468934999995,
  "dvars_vstd": 1.018898434214285,
  "efc": 0.575312185633266,
  "fber": 1507.20849609375,
  "fd_mean": 0.10300899408050408,
  "fd_num": 5,
  "fd_perc": 3.5460992907801416,
  "fwhm_avg": 1.675285465226188,
  "fwhm_x": 1.5427833333333334,
  "fwhm_y": 1.7781633333333333,
  "fwhm_z": 1.7049097290118966,
  "gcor": 0.0120192,
  "gsr_x": -0.004115808289498091,
  "gsr_y": 0.02518141269683838,
  "provenance": {
    "md5sum": "d6e8d4c2c3584f4c34fa70009b9c9275",
    "settings": {
      "fd_thres": 0.2,
      "testing": false
    },
    "software": "mriqc",
    "version": "22.0.6",
    "webapi_port": null,
    "webapi_url": "https://mriqc.nimh.nih.gov/api/v1"
  },
  "size_t": 141,
  "size_x": 64,
  "size_y": 64,
  "size_z": 36,
  "snr": 6.156629452616742,
  "spacing_tr": 2.0,
  "spacing_x": 3.0,
  "spacing_y": 3.0,
  "spacing_z": 3.000000476837158,
  "summary_bg_k": 28.574701370216626,
  "summary_bg_mad": 10.704176325559365,
  "summary_bg_mean": 40.63551330566406,
  "summary_bg_median": 19.751771926879883,
  "summary_bg_n": 79139.0,
  "summary_bg_p05": 9.80141830444336,
  "summary_bg_p95": 140.63119506835938,
  "summary_bg_stdv": 67.85416412353516,
  "summary_fg_k": 3.3756872872972847,
  "summary_fg_mad": 109.88078667455382,
  "summary_fg_mean": 792.2097778320312,
  "summary_fg_median": 775.5602416992188,
  "summary_fg_n": 36075.0,
  "summary_fg_p05": 632.7737609863282,
  "summary_fg_p95": 1001.886474609375,
  "summary_fg_stdv": 125.96981811523438,
  "tsnr": 62.97063502832316
}