{
  "aor": 0.005937957746478872,
  "aqi": 0.02638977253521127,
  "bids_meta": {
    "EchoTime": 0.03,
    "FlipAngle": 71,
    "RepetitionTime": 2,
    "SliceTiming": [
      1,
      0,
      1.055,
      0.055,
      1.11,
      0.11,
      1.165,
      0.165,
      1.22,
      0.2225,
      1.2775,
      0.2775,
      1.3325,
      0.3325,
      1.3875,
      0.3875,
      1.4425,
      0.4425,
      1.5,
      0.5,
      1.555,
      0.555,
      1.61,
      0.61,
      1.665,
      0.665,
      1.72,
      0.72,
      1.7775,
      0.7775,
      1.8325,
      0.8325,
      1.8875,
      0.8875,
      1.9425,
      0.9425
    ],
    "TaskName": "Study-Test",
    "dataset": "ds001745",
    "modality": "bold",
    "run_id": 2,
    "subject_id": "18",
    "task_id": "StudyTest"
  },
  "dummy_trs": 0,
  "dvars_nstd": 24.101605733191498,
  "dvars_std": 1.1085143796453891,
  "dvars_vstd": 0.9981003299290779,
  "efc": 0.5640709952208393,
  "fber": 1365.6163330078125,
  "fd_mean": 0.15984827160294132,
  "fd_num": 29,
  "fd_perc": 20.422535211267604,
  "fwhm_avg": 1.7052844004448289,
  "fwhm_x": 1.6175266666666666,
  "fwhm_y": 1.8373966666666668,
  "fwhm_z": 1.6609298680011535,
  "gcor": 0.0138725,
  "gsr_x": -0.0032556012738496065,
  "gsr_y": 0.03309706971049309,
  "provenance": {
    "md5sum": "83398e8e3fada90c05a5c776894d1abe",
    "settings": {
      "fd_thres": 0.2,
      "testing": false
    },
    "software": "mriqc",
    "version": "22.0.6",
    "webapi_port": null,
    "webapi_url": "https://mriqc.nimh.nih.gov/api/v1"
  },
  "size_t": 142,
  "size_x": 64,
  "size_y": 64,
  "size_z": 36,
  "snr": 7.115258161303075,
  "spacing_tr": 2.0,
  "spacing_x": 3.0,
  "spacing_y": 3.0,
  "spacing_z": 3.000000238418579,
  "summary_bg_k": 29.94928446926106,
  "summary_bg_mad": 16.078926085645392,
  "summary_bg_mean": 49.97953414916992,
  "summary_bg_median": 22.626760482788086,
  "summary_bg_n": 82368.0,
  "summary_bg_p05": 9.176055908203125,
  "summary_bg_p95": 184.59999771118132,
  "summary_bg_stdv": 85.67433166503906,
  "summary_fg_k": 3.8458572711876826,
  "summary_fg_mad": 103.16618402455671,
  "summary_fg_mean": 859.95751953125,
  "summary_fg_median": 849.225341796875,
  "summary_fg_n": 32407.0,
  "summary_fg_p05": 700.565478515625,
  "summary_fg_p95": 1053.8499633789063,
  "summary_fg_stdv": 119.35086822509766,
  "tsnr": 42.82723646610975
}